alphagenome_pytorch/__init__.py
alphagenome_pytorch/alphagenome.py
alphagenome_pytorch/config.py
alphagenome_pytorch/data.py
alphagenome_pytorch/convert/__init__.py
alphagenome_pytorch/convert/convert_checkpoint.py
alphagenome_pytorch/convert/inspect_jax.py
alphagenome_pytorch/convert/inspect_torch.py
alphagenome_pytorch/convert/mapping_spec.py
alphagenome_pytorch/convert/shape_transforms.py
alphagenome_pytorch-0.2.6.dist-info/METADATA
alphagenome_pytorch-0.2.6.dist-info/WHEEL
alphagenome_pytorch-0.2.6.dist-info/licenses/LICENSE
alphagenome_pytorch-0.2.6.dist-info/RECORD
