Metadata-Version: 2.4
Name: alphagenome-pytorch
Version: 0.2.6
Summary: AlphaGenome
Project-URL: Homepage, https://pypi.org/project/alphagenome-pytorch/
Project-URL: Repository, https://github.com/lucidrains/alphagenome
Author-email: Phil Wang <lucidrains@gmail.com>
License: MIT License
License-File: LICENSE
Keywords: artificial intelligence,attention mechanism,deep learning,genomics,splicing,transformers
Classifier: Development Status :: 4 - Beta
Classifier: Intended Audience :: Developers
Classifier: License :: OSI Approved :: MIT License
Classifier: Programming Language :: Python :: 3.11
Classifier: Topic :: Scientific/Engineering :: Artificial Intelligence
Requires-Python: >=3.11
Requires-Dist: accelerate
Requires-Dist: einops>=0.8.0
Requires-Dist: einx>=0.3.0
Requires-Dist: pope-pytorch>=0.0.9
Requires-Dist: torch-einops-utils
Requires-Dist: torch>=2.4
Provides-Extra: convert
Requires-Dist: aiohttp; extra == 'convert'
Requires-Dist: dm-haiku; extra == 'convert'
Requires-Dist: einshape; extra == 'convert'
Requires-Dist: huggingface-hub; extra == 'convert'
Requires-Dist: jax[cpu]; extra == 'convert'
Requires-Dist: jmp; extra == 'convert'
Requires-Dist: orbax-checkpoint; extra == 'convert'
Provides-Extra: example
Requires-Dist: pyyaml; extra == 'example'
Provides-Extra: test
Requires-Dist: pytest; extra == 'test'
Requires-Dist: scipy; extra == 'test'
